dotxboxcontroller/__init__.py
dotxboxcontroller/xboxcontroller.py
dotxboxcontroller-0.0.1.dist-info/METADATA
dotxboxcontroller-0.0.1.dist-info/WHEEL
dotxboxcontroller-0.0.1.dist-info/top_level.txt
dotxboxcontroller-0.0.1.dist-info/RECORD
