Metadata-Version: 2.1
Name: dotxboxcontroller
Version: 0.0.1
Summary: Getting input from Microsoft XBox 360 controllers via the XInput library on Windows.
Home-page: https://github.com/uncertainty-cc/dotXboxController
Author: Rath Robotics
Author-email: tk@uncertainty.email
Classifier: Programming Language :: Python :: 3
Classifier: License :: OSI Approved :: MIT License
Classifier: Operating System :: OS Independent
Requires-Python: >=3.6
Requires-Dist: pyglet
